uniqk/__init__.py
uniqk/models/__init__.py
uniqk/models/bert/configuration_bert.py
uniqk/models/bert/modeling_bert.py
uniqk/models/gpt2/configuration_gpt2.py
uniqk/models/gpt2/modeling_gpt2.py
uniqk-1.0.1.dist-info/METADATA
uniqk-1.0.1.dist-info/WHEEL
uniqk-1.0.1.dist-info/RECORD
